smpp/__init__.py
smpp/pdu/__init__.py
smpp/pdu/constants.py
smpp/pdu/encoding.py
smpp/pdu/error.py
smpp/pdu/gsm_constants.py
smpp/pdu/gsm_encoding.py
smpp/pdu/gsm_types.py
smpp/pdu/operations.py
smpp/pdu/pdu_encoding.py
smpp/pdu/pdu_types.py
smpp/pdu/sm_encoding.py
smpp/pdu/smpp_time.py
smpp.pdu3-0.6.dist-info/LICENSE
smpp.pdu3-0.6.dist-info/METADATA
smpp.pdu3-0.6.dist-info/WHEEL
smpp.pdu3-0.6.dist-info/top_level.txt
smpp.pdu3-0.6.dist-info/RECORD
